LICENSE
eodhdc/__init__.py
eodhdc/base.py
eodhdc/clients/__init__.py
eodhdc/clients/aiohttp.py
eodhdc/clients/httpxa.py
eodhdc/clients/httpxs.py
eodhdc/clients/requests.py
eodhdc/eodhdc.py
eodhdc/eodhdws.py
eodhdc/exceptions.py
eodhdc/groups/__init__.py
eodhdc/groups/coro/__init__.py
eodhdc/groups/coro/alternative.py
eodhdc/groups/coro/exchange.py
eodhdc/groups/coro/fundamental.py
eodhdc/groups/coro/market.py
eodhdc/groups/sync/__init__.py
eodhdc/groups/sync/alternative.py
eodhdc/groups/sync/exchange.py
eodhdc/groups/sync/fundamental.py
eodhdc/groups/sync/market.py
eodhdc-1.1.0.dist-info/WHEEL
eodhdc-1.1.0.dist-info/LICENSE
eodhdc-1.1.0.dist-info/METADATA
eodhdc-1.1.0.dist-info/RECORD
