Metadata-Version: 2.1
Name: eodhdc
Version: 1.1.0
Summary: EOD Historical Data API Python Client
Home-page: https://github.com/wargx/eodhdc
License: MIT
Keywords: eod,eodhd,financial,historical,economic,data,api,fundamental,alternative,insider,real-time,exchanges,capitalization,bulk,intraday,options
Author: Warg
Author-email: warg.silencer@gmail.com
Requires-Python: >=3.7.16,<4.0.0
Classifier: Development Status :: 5 - Production/Stable
Classifier: Intended Audience :: Developers
Classifier: License :: OSI Approved :: MIT License
Classifier: Operating System :: OS Independent
Classifier: Programming Language :: Python :: 3
Classifier: Programming Language :: Python :: 3.8
Classifier: Programming Language :: Python :: 3.9
Classifier: Programming Language :: Python :: 3.10
Classifier: Programming Language :: Python :: 3.11
Classifier: Programming Language :: Python :: 3
Classifier: Programming Language :: Python :: 3.10
Classifier: Programming Language :: Python :: 3.11
Classifier: Programming Language :: Python :: 3.7
Classifier: Programming Language :: Python :: 3.8
Classifier: Programming Language :: Python :: 3.9
Provides-Extra: aiohttp
Provides-Extra: httpx
Requires-Dist: aiohttp (>=3.8.3,<4.0.0) ; extra == "aiohttp"
Requires-Dist: httpx (>=0.23.3,<0.24.0) ; extra == "httpx"
Requires-Dist: pandas (>=1.3,<2.0)
Requires-Dist: requests (>=2.28.2,<3.0.0)
Requires-Dist: websockets (>=10.4,<11.0)
Project-URL: Repository, https://github.com/wargx/eodhdc
